odoo/addons/hr_contract_currency/README.rst
odoo/addons/hr_contract_currency/__init__.py
odoo/addons/hr_contract_currency/__manifest__.py
odoo/addons/hr_contract_currency/i18n/de.po
odoo/addons/hr_contract_currency/i18n/es.po
odoo/addons/hr_contract_currency/i18n/fr.po
odoo/addons/hr_contract_currency/i18n/hr.po
odoo/addons/hr_contract_currency/i18n/hr_contract_currency.pot
odoo/addons/hr_contract_currency/i18n/it.po
odoo/addons/hr_contract_currency/models/__init__.py
odoo/addons/hr_contract_currency/models/hr_contract.py
odoo/addons/hr_contract_currency/readme/CONTRIBUTORS.rst
odoo/addons/hr_contract_currency/readme/DESCRIPTION.rst
odoo/addons/hr_contract_currency/static/description/icon.png
odoo/addons/hr_contract_currency/static/description/index.html
odoo/addons/hr_contract_currency/tests/__init__.py
odoo/addons/hr_contract_currency/tests/test_hr_contract_currency.py
odoo/addons/hr_contract_currency/views/hr_contract.xml
odoo14_addon_hr_contract_currency-14.0.1.0.1.dev14.dist-info/METADATA
odoo14_addon_hr_contract_currency-14.0.1.0.1.dev14.dist-info/WHEEL
odoo14_addon_hr_contract_currency-14.0.1.0.1.dev14.dist-info/top_level.txt
odoo14_addon_hr_contract_currency-14.0.1.0.1.dev14.dist-info/RECORD
